pydracor/__init__.py
pydracor/api_wrapper.py
pydracor/dracor_func.txt
pydracor-3.0.2.dist-info/METADATA
pydracor-3.0.2.dist-info/WHEEL
pydracor-3.0.2.dist-info/licenses/LICENSE.txt
pydracor-3.0.2.dist-info/RECORD
