Metadata-Version: 2.4
Name: pydracor
Version: 3.0.2
Summary: Python package which wraps methods from pydracor-base to interact with the DraCor API.
Project-URL: Repository, https://github.com/dracor-org/pydracor.git
Author-email: "Henny Sluyter-Gäthje, Eduard Grigoriev" <sluytergaeth@uni-potsdam.de>
Maintainer-email: Henny Sluyter-Gäthje <sluytergaeth@uni-potsdam.de>
License-Expression: MIT
License-File: LICENSE.txt
Keywords: API,Corpus,DraCor,Drama,Drama Corpus,Wrapper,pydracor
Classifier: Development Status :: 4 - Beta
Classifier: Intended Audience :: Developers
Classifier: Intended Audience :: Education
Classifier: Intended Audience :: Science/Research
Classifier: License :: OSI Approved :: MIT License
Classifier: Programming Language :: Python
Classifier: Programming Language :: Python :: 3 :: Only
Classifier: Programming Language :: Python :: 3.8
Classifier: Programming Language :: Python :: 3.9
Classifier: Programming Language :: Python :: 3.10
Classifier: Programming Language :: Python :: 3.11
Classifier: Programming Language :: Python :: 3.12
Classifier: Topic :: Education
Classifier: Topic :: Software Development
Classifier: Topic :: Software Development :: Libraries
Classifier: Topic :: Software Development :: Libraries :: Python Modules
Requires-Python: >=3.8
Requires-Dist: pydracor-base==1.0.1
